tap_kiotviet/__init__.py
tap_kiotviet/client.py
tap_kiotviet/kiotviet_paginator.py
tap_kiotviet/schemas/branches.json
tap_kiotviet/schemas/customers.json
tap_kiotviet/schemas/invoices.json
tap_kiotviet/schemas/orders.json
tap_kiotviet/schemas/products.json
tap_kiotviet/schemas/purchase_orders.json
tap_kiotviet/schemas/returns.json
tap_kiotviet/schemas/users.json
tap_kiotviet/streams/BranchesStream.py
tap_kiotviet/streams/CustomersStream.py
tap_kiotviet/streams/InvoicesStream.py
tap_kiotviet/streams/OrdersStream.py
tap_kiotviet/streams/ProductsStream.py
tap_kiotviet/streams/PurchaseOrdersStream.py
tap_kiotviet/streams/ReturnsStream.py
tap_kiotviet/streams/UsersStream.py
tap_kiotviet/streams/__init__.py
tap_kiotviet/tap.py
tap_kiotviet-0.0.1.dist-info/LICENSE
tap_kiotviet-0.0.1.dist-info/METADATA
tap_kiotviet-0.0.1.dist-info/WHEEL
tap_kiotviet-0.0.1.dist-info/entry_points.txt
tap_kiotviet-0.0.1.dist-info/RECORD
