Metadata-Version: 2.1
Name: tap-kiotviet
Version: 0.0.1
Summary: `tap-kiotviet` is a Singer tap for KiotViet, built with the Meltano Singer SDK.
License: Apache-2.0
Keywords: ELT,KiotViet
Author: ChienLe
Author-email: lchien063@gmail.com
Requires-Python: >=3.8,<4
Classifier: License :: OSI Approved :: Apache Software License
Classifier: Programming Language :: Python :: 3
Classifier: Programming Language :: Python :: 3.8
Classifier: Programming Language :: Python :: 3.9
Classifier: Programming Language :: Python :: 3.10
Classifier: Programming Language :: Python :: 3.11
Provides-Extra: s3
Requires-Dist: fs-s3fs (>=1.1.1,<1.2.0) ; extra == "s3"
Requires-Dist: requests (>=2.31.0,<2.32.0)
Requires-Dist: singer-sdk (>=0.34.1,<0.35.0)
